rzpipe/__init__.py
rzpipe/native.py
rzpipe/open_async.py
rzpipe/open_base.py
rzpipe/open_sync.py
rzpipe-0.6.2.dist-info/LICENSE
rzpipe-0.6.2.dist-info/METADATA
rzpipe-0.6.2.dist-info/WHEEL
rzpipe-0.6.2.dist-info/top_level.txt
rzpipe-0.6.2.dist-info/RECORD
