Metadata-Version: 2.1
Name: rzpipe
Version: 0.6.2
Summary: Pipe interface for rizin
Home-page: https://rizin.re
Author: rizinorg
Author-email: info@rizin.re
License: MIT
Classifier: License :: OSI Approved :: MIT License
Classifier: Programming Language :: Python :: 3
Classifier: Operating System :: OS Independent
Classifier: Topic :: Security
Classifier: Topic :: Software Development :: Assemblers
Classifier: Topic :: Software Development :: Debuggers
Classifier: Topic :: Software Development :: Disassemblers
License-File: LICENSE
